VisaGen/__init__.py
VisaGen/intergraph_final.py
VisaGen/portrait_robot_final.py
visagen-0.1.1.dist-info/licenses/LICENSE
visagen-0.1.1.dist-info/METADATA
visagen-0.1.1.dist-info/WHEEL
visagen-0.1.1.dist-info/top_level.txt
visagen-0.1.1.dist-info/RECORD
